setup.py
vgmdb_wrapper/__init__.py
vgmdb_wrapper/client.py
vgmdb_wrapper/information.py
vgmdb_wrapper/search.py
vgmdb_wrapper/utils.py
vgmdb_wrapper.egg-info/PKG-INFO
vgmdb_wrapper.egg-info/SOURCES.txt
vgmdb_wrapper.egg-info/dependency_links.txt
vgmdb_wrapper.egg-info/top_level.txt