Metadata-Version: 1.1
Name: vgmdb-wrapper
Version: 0.0.1
Summary: VGMdb API Wrapper for Python.
Home-page: https://github.com/kinformation/vgmdb_wrapper
Author: Kanatani Kazuya
Author-email: kanatani.devel@gmail.com
License: MIT License
Keywords: vgmdb
Platform: UNKNOWN
Classifier: Development Status :: 1 - Planning
Classifier: License :: OSI Approved :: MIT License
Classifier: Programming Language :: Python :: 2 :: Only
Classifier: Topic :: Software Development
